app_launcher.py
app/__init__.py
app/_version.py
app/analyzer.py
app/routes.py
app/static/css/d3-lineage.css
app/static/css/lineage.css
app/static/css/styles.css
app/static/img/logo.png
app/static/js/app.js
app/static/js/d3-lineage.js
app/static/js/lineage.js
app/templates/expensive_queries.html
app/templates/index.html
app/templates/lineage.html
app/templates/query_details.html
app/templates/table_details.html
app/templates/table_stats.html
pg_lineagelens-1.0.3.dist-info/LICENSE
pg_lineagelens-1.0.3.dist-info/METADATA
pg_lineagelens-1.0.3.dist-info/WHEEL
pg_lineagelens-1.0.3.dist-info/entry_points.txt
pg_lineagelens-1.0.3.dist-info/top_level.txt
pg_lineagelens-1.0.3.dist-info/RECORD
