Metadata-Version: 2.2
Name: pg_lineagelens
Version: 1.0.3
Summary: PostgreSQL Query Lineage and Performance Analyzer
Home-page: https://github.com/somasundaram/pg_lineage
Author: Somasundaram Sekar
Author-email: somasundaram@outlook.com
Keywords: postgresql,sql,query analysis,performance,lineage
Classifier: Development Status :: 4 - Beta
Classifier: Intended Audience :: Developers
Classifier: Intended Audience :: Information Technology
Classifier: Intended Audience :: System Administrators
Classifier: License :: OSI Approved :: MIT License
Classifier: Programming Language :: Python :: 3
Classifier: Programming Language :: Python :: 3.8
Classifier: Programming Language :: Python :: 3.9
Classifier: Programming Language :: Python :: 3.10
Classifier: Programming Language :: Python :: 3.11
Classifier: Programming Language :: Python :: 3.12
Classifier: Operating System :: OS Independent
Classifier: Topic :: Database
Classifier: Topic :: Software Development :: Libraries :: Python Modules
Requires-Python: >=3.8
License-File: LICENSE
Requires-Dist: flask>=2.0.0
Requires-Dist: psycopg2-binary>=2.9.0
Requires-Dist: pandas>=1.3.0
Requires-Dist: networkx>=2.6.0
Requires-Dist: matplotlib>=3.4.0
Requires-Dist: sqlparse>=0.4.0
Requires-Dist: waitress>=2.0.0
Dynamic: author
Dynamic: author-email
Dynamic: classifier
Dynamic: description
Dynamic: description-content-type
Dynamic: home-page
Dynamic: keywords
Dynamic: requires-dist
Dynamic: requires-python
Dynamic: summary
